{
  "date": "2026-05-09",
  "generated_at": "2026-05-09T16:55:15.418147Z",
  "races": [
    {
      "id": "leicester-1755",
      "course": "Leicester",
      "time": "17:55",
      "title": "British Ebf Novice Stakes",
      "distance": "7f",
      "going": "Good to Firm",
      "race_class": "",
      "prize": "",
      "num_runners": 9,
      "ew_places": 3,
      "date": "2026-05-09",
      "runners": [
        {
          "horse": "MASKED WARRIOR",
          "country": "GB",
          "jockey": "Darragh Keenan",
          "trainer": "William Haggas",
          "form": "32-",
          "age": "3",
          "weight": "9-7",
          "draw": "",
          "odds_str": "11/8",
          "odds_dec": 2.38,
          "silk_url": "https://images.timeform.com/silks/opt/00004756.png",
          "score": 75.3,
          "components": {
            "odds_value": 100,
            "recent_form": 75.0,
            "consistency": 100.0,
            "jockey": 60.0,
            "weight": 0.0,
            "absence_pen": 0.0,
            "going_factor": 1.05
          },
          "recommendation": {
            "type": "Win",
            "confidence": 75,
            "label": "Strong Win Bet",
            "reasoning": "strong recent form; placed last time out; consistent placer (100% placed); short price reflects market confidence"
          }
        },
        {
          "horse": "KING&#39;S CAVALRY",
          "country": "GB",
          "jockey": "Luke Morris",
          "trainer": "James Tate",
          "form": "6-2",
          "age": "3",
          "weight": "9-7",
          "draw": "",
          "odds_str": "5/6",
          "odds_dec": 1.91,
          "silk_url": "https://images.timeform.com/silks/opt/00000157.png",
          "score": 63.3,
          "components": {
            "odds_value": 100,
            "recent_form": 61.7,
            "consistency": 50.0,
            "jockey": 60.0,
            "weight": 0.0,
            "absence_pen": 0.0,
            "going_factor": 1.05
          },
          "recommendation": {
            "type": "Win",
            "confidence": 63,
            "label": "Win Bet",
            "reasoning": "solid recent form; placed last time out; consistent placer (50% placed); short price reflects market confidence"
          }
        },
        {
          "horse": "DISTANT MOON",
          "country": "IRE",
          "jockey": "Sean Dylan Bowen",
          "trainer": "Saeed bin Suroor",
          "form": "",
          "age": "3",
          "weight": "9-7",
          "draw": "",
          "odds_str": "13/2",
          "odds_dec": 7.5,
          "silk_url": "https://images.timeform.com/silks/opt/00012133.png",
          "score": 31.0,
          "components": {
            "odds_value": 33.3,
            "recent_form": 40.0,
            "consistency": 0,
            "jockey": 60.0,
            "weight": 0.0,
            "absence_pen": 0.0,
            "going_factor": 1.05
          },
          "recommendation": {
            "type": "Skip",
            "confidence": 12,
            "label": "Skip",
            "reasoning": "moderate form"
          }
        },
        {
          "horse": "GALBA",
          "country": "GB",
          "jockey": "Sam Hitchcott",
          "trainer": "Richard Hannon",
          "form": "3-7",
          "age": "3",
          "weight": "9-7",
          "draw": "",
          "odds_str": "28/1",
          "odds_dec": 29.0,
          "silk_url": "https://images.timeform.com/silks/opt/00069643B.png",
          "score": 29.7,
          "components": {
            "odds_value": 0.4,
            "recent_form": 38.3,
            "consistency": 50.0,
            "jockey": 60.0,
            "weight": 0.0,
            "absence_pen": 0.0,
            "going_factor": 1.05
          },
          "recommendation": {
            "type": "Skip",
            "confidence": 11,
            "label": "Skip",
            "reasoning": "moderate form; consistent placer (50% placed)"
          }
        },
        {
          "horse": "BRIDGET&#39;S BABY",
          "country": "GB",
          "jockey": "William Carson",
          "trainer": "Tony Carroll",
          "form": "06-",
          "age": "3",
          "weight": "9-2",
          "draw": "",
          "odds_str": "SP",
          "odds_dec": 301.0,
          "silk_url": "https://images.timeform.com/silks/opt/00830733.png",
          "score": 26.0,
          "components": {
            "odds_value": 0,
            "recent_form": 20.0,
            "consistency": 0,
            "jockey": 60.0,
            "weight": 100.0,
            "absence_pen": 0.0,
            "going_factor": 1.05
          },
          "recommendation": {
            "type": "Skip",
            "confidence": 10,
            "label": "Skip",
            "reasoning": "poor recent form"
          }
        },
        {
          "horse": "ABLE ASTRA",
          "country": "IRE",
          "jockey": "Jack Nicholls",
          "trainer": "Clive Cox",
          "form": "8-",
          "age": "3",
          "weight": "9-2",
          "draw": "",
          "odds_str": "33/1",
          "odds_dec": 34.0,
          "silk_url": "https://images.timeform.com/silks/opt/00859678.png",
          "score": 22.9,
          "components": {
            "odds_value": 0,
            "recent_form": 10.0,
            "consistency": 0,
            "jockey": 60.0,
            "weight": 100.0,
            "absence_pen": 0.0,
            "going_factor": 1.05
          },
          "recommendation": {
            "type": "Skip",
            "confidence": 9,
            "label": "Skip",
            "reasoning": "poor recent form"
          }
        },
        {
          "horse": "ASHLEY POOL",
          "country": "GB",
          "jockey": "Kieran O'Neill",
          "trainer": "Pam Sly",
          "form": "0",
          "age": "3",
          "weight": "9-2",
          "draw": "",
          "odds_str": "SP",
          "odds_dec": 251.0,
          "silk_url": "https://images.timeform.com/silks/opt/00853369.png",
          "score": 22.9,
          "components": {
            "odds_value": 0,
            "recent_form": 10.0,
            "consistency": 0,
            "jockey": 60.0,
            "weight": 100.0,
            "absence_pen": 0.0,
            "going_factor": 1.05
          },
          "recommendation": {
            "type": "Skip",
            "confidence": 9,
            "label": "Skip",
            "reasoning": "poor recent form"
          }
        },
        {
          "horse": "RACE TO THE EDGE",
          "country": "GB",
          "jockey": "Non Runner",
          "trainer": "Roger Varian",
          "form": "",
          "age": "3",
          "weight": "9-7",
          "draw": "",
          "odds_str": "SP",
          "odds_dec": 999.0,
          "silk_url": "https://images.timeform.com/silks/opt/00847648.png",
          "score": 22.3,
          "components": {
            "odds_value": 0,
            "recent_form": 40.0,
            "consistency": 0,
            "jockey": 60.0,
            "weight": 0.0,
            "absence_pen": 0.0,
            "going_factor": 1.05
          },
          "recommendation": {
            "type": "Skip",
            "confidence": 8,
            "label": "Skip",
            "reasoning": "moderate form"
          }
        },
        {
          "horse": "BLAZING SAM",
          "country": "GB",
          "jockey": "Gina Mangan",
          "trainer": "Georgina Nicholls",
          "form": "0",
          "age": "3",
          "weight": "9-7",
          "draw": "",
          "odds_str": "80/1",
          "odds_dec": 81.0,
          "silk_url": "https://images.timeform.com/silks/opt/00890510.png",
          "score": 12.9,
          "components": {
            "odds_value": 0,
            "recent_form": 10.0,
            "consistency": 0,
            "jockey": 60.0,
            "weight": 0.0,
            "absence_pen": 0.0,
            "going_factor": 1.05
          },
          "recommendation": {
            "type": "Skip",
            "confidence": 5,
            "label": "Skip",
            "reasoning": "poor recent form"
          }
        }
      ]
    },
    {
      "id": "warwick-1807",
      "course": "Warwick",
      "time": "18:07",
      "title": "Mike Mohans 60Th Birthday National Hunt Maiden Hurdle",
      "distance": "2m",
      "going": "Good to Firm",
      "race_class": "",
      "prize": "",
      "num_runners": 8,
      "ew_places": 3,
      "date": "2026-05-09",
      "runners": [
        {
          "horse": "TARANIS DUBH",
          "country": "GB",
          "jockey": "Gavin Sheehan",
          "trainer": "Olly Murphy",
          "form": "3-",
          "age": "5",
          "weight": "11-5",
          "draw": "",
          "odds_str": "6/4",
          "odds_dec": 2.5,
          "silk_url": "https://images.timeform.com/silks/opt/00892568.png",
          "score": 72.2,
          "components": {
            "odds_value": 100,
            "recent_form": 65.0,
            "consistency": 100.0,
            "jockey": 60.0,
            "weight": 0.0,
            "absence_pen": 0.0,
            "going_factor": 1.05
          },
          "recommendation": {
            "type": "Win",
            "confidence": 72,
            "label": "Strong Win Bet",
            "reasoning": "solid recent form; consistent placer (100% placed); short price reflects market confidence"
          }
        },
        {
          "horse": "SKY GROVE",
          "country": "IRE",
          "jockey": "Bryan Carver",
          "trainer": "Laura Horsfall",
          "form": "3-",
          "age": "5",
          "weight": "11-5",
          "draw": "",
          "odds_str": "12/1",
          "odds_dec": 13.0,
          "silk_url": "https://images.timeform.com/silks/opt/00080569A.png",
          "score": 49.8,
          "components": {
            "odds_value": 11.7,
            "recent_form": 65.0,
            "consistency": 100.0,
            "jockey": 65.0,
            "weight": 0.0,
            "absence_pen": 0.0,
            "going_factor": 1.05
          },
          "recommendation": {
            "type": "Skip",
            "confidence": 19,
            "label": "Skip",
            "reasoning": "solid recent form; consistent placer (100% placed)"
          }
        },
        {
          "horse": "DUNSTALL STAR",
          "country": "GB",
          "jockey": "Charlie Deutsch",
          "trainer": "Tom George",
          "form": "61-",
          "age": "5",
          "weight": "11-5",
          "draw": "",
          "odds_str": "18/1",
          "odds_dec": 19.0,
          "silk_url": "https://images.timeform.com/silks/opt/00057395.png",
          "score": 45.9,
          "components": {
            "odds_value": 4.5,
            "recent_form": 86.2,
            "consistency": 50.0,
            "jockey": 60.0,
            "weight": 0.0,
            "absence_pen": 0.0,
            "going_factor": 1.05
          },
          "recommendation": {
            "type": "Skip",
            "confidence": 18,
            "label": "Skip",
            "reasoning": "strong recent form; won last time out; consistent placer (50% placed)"
          }
        },
        {
          "horse": "SO PROUD",
          "country": "IRE",
          "jockey": "Lorcan Williams",
          "trainer": "Jonjo & A.J. O'Neill",
          "form": "15-",
          "age": "5",
          "weight": "11-5",
          "draw": "",
          "odds_str": "6/1",
          "odds_dec": 7.0,
          "silk_url": "https://images.timeform.com/silks/opt/00045067.png",
          "score": 44.7,
          "components": {
            "odds_value": 31.2,
            "recent_form": 60.0,
            "consistency": 50.0,
            "jockey": 60.0,
            "weight": 0.0,
            "absence_pen": 0.0,
            "going_factor": 1.05
          },
          "recommendation": {
            "type": "Skip",
            "confidence": 17,
            "label": "Skip",
            "reasoning": "solid recent form; consistent placer (50% placed)"
          }
        },
        {
          "horse": "KAP DE CERISY",
          "country": "FR",
          "jockey": "Charlie Todd",
          "trainer": "Dan Skelton",
          "form": "",
          "age": "6",
          "weight": "10-12",
          "draw": "",
          "odds_str": "8/1",
          "odds_dec": 9.0,
          "silk_url": "https://images.timeform.com/silks/opt/00892548.png",
          "score": 38.0,
          "components": {
            "odds_value": 21.8,
            "recent_form": 40.0,
            "consistency": 0,
            "jockey": 60.0,
            "weight": 100.0,
            "absence_pen": 0.0,
            "going_factor": 1.05
          },
          "recommendation": {
            "type": "Skip",
            "confidence": 15,
            "label": "Skip",
            "reasoning": "moderate form"
          }
        },
        {
          "horse": "WINGS OF AYRTON",
          "country": "IRE",
          "jockey": "Ben Jones",
          "trainer": "Ben Pauling",
          "form": "",
          "age": "5",
          "weight": "11-5",
          "draw": "",
          "odds_str": "10/3",
          "odds_dec": 4.33,
          "silk_url": "https://images.timeform.com/silks/opt/00893098.png",
          "score": 37.3,
          "components": {
            "odds_value": 57.3,
            "recent_form": 40.0,
            "consistency": 0,
            "jockey": 60.0,
            "weight": 0.0,
            "absence_pen": 0.0,
            "going_factor": 1.05
          },
          "recommendation": {
            "type": "Skip",
            "confidence": 14,
            "label": "Skip",
            "reasoning": "moderate form"
          }
        },
        {
          "horse": "FINE FELLOW",
          "country": "GB",
          "jockey": "Tom Broughton",
          "trainer": "Alastair Ralph",
          "form": "38-",
          "age": "6",
          "weight": "11-5",
          "draw": "",
          "odds_str": "66/1",
          "odds_dec": 67.0,
          "silk_url": "https://images.timeform.com/silks/opt/00002214.png",
          "score": 26.5,
          "components": {
            "odds_value": 0,
            "recent_form": 28.3,
            "consistency": 50.0,
            "jockey": 60.0,
            "weight": 0.0,
            "absence_pen": 0.0,
            "going_factor": 1.05
          },
          "recommendation": {
            "type": "Skip",
            "confidence": 10,
            "label": "Skip",
            "reasoning": "poor recent form; consistent placer (50% placed)"
          }
        },
        {
          "horse": "PETER&#39;S LAST DEAL",
          "country": "FR",
          "jockey": "Caoilin Quinn",
          "trainer": "Tom Symonds",
          "form": "35/36-",
          "age": "5",
          "weight": "11-5",
          "draw": "",
          "odds_str": "17/2",
          "odds_dec": 9.5,
          "silk_url": "https://images.timeform.com/silks/opt/00870586.png",
          "score": 20.4,
          "components": {
            "odds_value": 20.1,
            "recent_form": 38.3,
            "consistency": 50.0,
            "jockey": 68.0,
            "weight": 0.0,
            "absence_pen": 15.0,
            "going_factor": 1.05
          },
          "recommendation": {
            "type": "Skip",
            "confidence": 8,
            "label": "Skip",
            "reasoning": "moderate form; consistent placer (50% placed); returning from long absence"
          }
        }
      ]
    },
    {
      "id": "hexham-1815",
      "course": "Hexham",
      "time": "18:15",
      "title": "Jennis Justatenner 50Th Celebrations Handicap Hurdle",
      "distance": "2m",
      "going": "Good to Firm",
      "race_class": "",
      "prize": "",
      "num_runners": 11,
      "ew_places": 3,
      "date": "2026-05-09",
      "runners": [
        {
          "horse": "SCOTS POET",
          "country": "GB",
          "jockey": "Conor O'Farrell",
          "trainer": "Ewan Whillans",
          "form": "34473331-",
          "age": "10",
          "weight": "11-5",
          "draw": "",
          "odds_str": "3/1",
          "odds_dec": 4.0,
          "silk_url": "https://images.timeform.com/silks/opt/00889136.png",
          "score": 73.6,
          "components": {
            "odds_value": 90.7,
            "recent_form": 85.1,
            "consistency": 62.5,
            "jockey": 60.0,
            "weight": 34.6,
            "absence_pen": 0.0,
            "going_factor": 1.05
          },
          "recommendation": {
            "type": "Win",
            "confidence": 73,
            "label": "Strong Win Bet",
            "reasoning": "solid recent form; won last time out; consistent placer (62% placed); each way option also viable"
          }
        },
        {
          "horse": "GEMINI MAN",
          "country": "IRE",
          "jockey": "Joshua Thompson",
          "trainer": "Iain Jardine",
          "form": "21269326-",
          "age": "8",
          "weight": "12-0",
          "draw": "",
          "odds_str": "4/1",
          "odds_dec": 5.0,
          "silk_url": "https://images.timeform.com/silks/opt/00891685.png",
          "score": 52.4,
          "components": {
            "odds_value": 70.4,
            "recent_form": 45.7,
            "consistency": 62.5,
            "jockey": 60.0,
            "weight": 0.0,
            "absence_pen": 0.0,
            "going_factor": 1.05
          },
          "recommendation": {
            "type": "EachWay",
            "confidence": 52,
            "label": "Each Way (Speculative)",
            "reasoning": "moderate form; consistent placer (62% placed)"
          }
        },
        {
          "horse": "LINDEN LANE",
          "country": "IRE",
          "jockey": "Ellis Collier",
          "trainer": "Mrs C. Williams",
          "form": "33867334-",
          "age": "6",
          "weight": "11-7",
          "draw": "",
          "odds_str": "6/1",
          "odds_dec": 7.0,
          "silk_url": "https://images.timeform.com/silks/opt/00885495.png",
          "score": 49.0,
          "components": {
            "odds_value": 47.1,
            "recent_form": 52.0,
            "consistency": 50.0,
            "jockey": 60.0,
            "weight": 26.9,
            "absence_pen": 0.0,
            "going_factor": 1.05
          },
          "recommendation": {
            "type": "Skip",
            "confidence": 19,
            "label": "Skip",
            "reasoning": "moderate form; consistent placer (50% placed)"
          }
        },
        {
          "horse": "MS CINDY KATE",
          "country": "IRE",
          "jockey": "Danny McMenamin",
          "trainer": "Nicky Richards",
          "form": "5844-",
          "age": "5",
          "weight": "11-2",
          "draw": "",
          "odds_str": "5/1",
          "odds_dec": 6.0,
          "silk_url": "https://images.timeform.com/silks/opt/00851867.png",
          "score": 42.1,
          "components": {
            "odds_value": 56.8,
            "recent_form": 41.0,
            "consistency": 0,
            "jockey": 60.0,
            "weight": 46.2,
            "absence_pen": 0.0,
            "going_factor": 1.05
          },
          "recommendation": {
            "type": "Skip",
            "confidence": 16,
            "label": "Skip",
            "reasoning": "moderate form"
          }
        },
        {
          "horse": "CLEAN GETAWAY",
          "country": "IRE",
          "jockey": "Joe Williamson",
          "trainer": "Philip Kirby",
          "form": "74224514-",
          "age": "9",
          "weight": "11-3",
          "draw": "",
          "odds_str": "17/2",
          "odds_dec": 999.0,
          "silk_url": "https://images.timeform.com/silks/opt/00884335.png",
          "score": 39.8,
          "components": {
            "odds_value": 0,
            "recent_form": 63.3,
            "consistency": 37.5,
            "jockey": 60.0,
            "weight": 42.3,
            "absence_pen": 0.0,
            "going_factor": 1.05
          },
          "recommendation": {
            "type": "Skip",
            "confidence": 15,
            "label": "Skip",
            "reasoning": "solid recent form"
          }
        },
        {
          "horse": "MR GLOBALIST",
          "country": "IRE",
          "jockey": "Sean Quinlan",
          "trainer": "Lizzie Quinlan",
          "form": "5655655-3",
          "age": "7",
          "weight": "10-2",
          "draw": "",
          "odds_str": "40/1",
          "odds_dec": 999.0,
          "silk_url": "https://images.timeform.com/silks/opt/00875483.png",
          "score": 36.3,
          "components": {
            "odds_value": 0,
            "recent_form": 46.3,
            "consistency": 12.5,
            "jockey": 60.0,
            "weight": 100.0,
            "absence_pen": 0.0,
            "going_factor": 1.05
          },
          "recommendation": {
            "type": "Skip",
            "confidence": 14,
            "label": "Skip",
            "reasoning": "moderate form"
          }
        },
        {
          "horse": "MALANGEN",
          "country": "IRE",
          "jockey": "Peter Kavanagh",
          "trainer": "Lisa Harrison",
          "form": "472883P7-",
          "age": "11",
          "weight": "10-12",
          "draw": "",
          "odds_str": "11/1",
          "odds_dec": 12.0,
          "silk_url": "https://images.timeform.com/silks/opt/00847132.png",
          "score": 32.4,
          "components": {
            "odds_value": 22.8,
            "recent_form": 23.3,
            "consistency": 20.5,
            "jockey": 60.0,
            "weight": 61.5,
            "absence_pen": 0.0,
            "going_factor": 1.05
          },
          "recommendation": {
            "type": "Skip",
            "confidence": 12,
            "label": "Skip",
            "reasoning": "poor recent form"
          }
        },
        {
          "horse": "KING SACRE",
          "country": "FR",
          "jockey": "James Davies",
          "trainer": "Nigel Hawke",
          "form": "46/5052-",
          "age": "6",
          "weight": "12-0",
          "draw": "",
          "odds_str": "5/1",
          "odds_dec": 6.0,
          "silk_url": "https://images.timeform.com/silks/opt/00851685A.png",
          "score": 30.1,
          "components": {
            "odds_value": 56.8,
            "recent_form": 50.0,
            "consistency": 25.0,
            "jockey": 70.0,
            "weight": 0.0,
            "absence_pen": 15.0,
            "going_factor": 1.05
          },
          "recommendation": {
            "type": "Skip",
            "confidence": 12,
            "label": "Skip",
            "reasoning": "moderate form; placed last time out; returning from long absence"
          }
        },
        {
          "horse": "ALVESTA",
          "country": "GB",
          "jockey": "Jonathon Bewley",
          "trainer": "George Bewley",
          "form": "2/4434446-",
          "age": "5",
          "weight": "10-10",
          "draw": "",
          "odds_str": "22/1",
          "odds_dec": 23.0,
          "silk_url": "https://images.timeform.com/silks/opt/00849343.png",
          "score": 18.3,
          "components": {
            "odds_value": 6.6,
            "recent_form": 42.7,
            "consistency": 14.3,
            "jockey": 60.0,
            "weight": 69.2,
            "absence_pen": 15.0,
            "going_factor": 1.05
          },
          "recommendation": {
            "type": "Skip",
            "confidence": 7,
            "label": "Skip",
            "reasoning": "moderate form; returning from long absence"
          }
        },
        {
          "horse": "KELLIE&#39;S DREAM",
          "country": "IRE",
          "jockey": "Callum Bewley",
          "trainer": "Daragh Bourke",
          "form": "5773/985-",
          "age": "9",
          "weight": "10-5",
          "draw": "",
          "odds_str": "11/1",
          "odds_dec": 12.0,
          "silk_url": "https://images.timeform.com/silks/opt/00870503.png",
          "score": 16.7,
          "components": {
            "odds_value": 22.8,
            "recent_form": 25.0,
            "consistency": 0,
            "jockey": 60.0,
            "weight": 88.5,
            "absence_pen": 15.0,
            "going_factor": 1.05
          },
          "recommendation": {
            "type": "Skip",
            "confidence": 6,
            "label": "Skip",
            "reasoning": "poor recent form; returning from long absence"
          }
        },
        {
          "horse": "WALK ON SON",
          "country": "IRE",
          "jockey": "Gregor Walkingshaw",
          "trainer": "Lucinda Russell & Michael Scudamore",
          "form": "89/734P98-",
          "age": "6",
          "weight": "11-11",
          "draw": "",
          "odds_str": "22/1",
          "odds_dec": 23.0,
          "silk_url": "https://images.timeform.com/silks/opt/00061704.png",
          "score": 4.2,
          "components": {
            "odds_value": 6.6,
            "recent_form": 17.0,
            "consistency": 12.4,
            "jockey": 60.0,
            "weight": 11.5,
            "absence_pen": 15.0,
            "going_factor": 1.05
          },
          "recommendation": {
            "type": "Skip",
            "confidence": 5,
            "label": "Skip",
            "reasoning": "poor recent form; returning from long absence"
          }
        }
      ]
    },
    {
      "id": "leicester-1825",
      "course": "Leicester",
      "time": "18:25",
      "title": "Smooth Radio Ladies Day 4Th July Book Now Handicap",
      "distance": "6f",
      "going": "Soft",
      "race_class": "",
      "prize": "",
      "num_runners": 6,
      "ew_places": 2,
      "date": "2026-05-09",
      "runners": [
        {
          "horse": "THIS FARH",
          "country": "GB",
          "jockey": "Rowan Scott",
          "trainer": "David Loughnane",
          "form": "3708-6461",
          "age": "4",
          "weight": "9-6",
          "draw": "",
          "odds_str": "5/2",
          "odds_dec": 3.5,
          "silk_url": "https://images.timeform.com/silks/opt/00834206.png",
          "score": 45.5,
          "components": {
            "odds_value": 52.4,
            "recent_form": 62.1,
            "consistency": 25.0,
            "jockey": 60.0,
            "weight": 50.0,
            "absence_pen": 0.0,
            "going_factor": 0.92
          },
          "recommendation": {
            "type": "Skip",
            "confidence": 18,
            "label": "Skip",
            "reasoning": "moderate form; won last time out"
          }
        },
        {
          "horse": "EMPEROR CARADOC",
          "country": "FR",
          "jockey": "David Nolan",
          "trainer": "Paul Midgley",
          "form": "03040-401",
          "age": "7",
          "weight": "9-11",
          "draw": "",
          "odds_str": "7/4",
          "odds_dec": 2.75,
          "silk_url": "https://images.timeform.com/silks/opt/00892288.png",
          "score": 43.5,
          "components": {
            "odds_value": 69.7,
            "recent_form": 58.3,
            "consistency": 25.0,
            "jockey": 60.0,
            "weight": 0.0,
            "absence_pen": 0.0,
            "going_factor": 0.92
          },
          "recommendation": {
            "type": "Skip",
            "confidence": 17,
            "label": "Skip",
            "reasoning": "moderate form; won last time out"
          }
        },
        {
          "horse": "FISCAL POLICY",
          "country": "IRE",
          "jockey": "James Sullivan",
          "trainer": "Ruth Carr",
          "form": "5995-6832",
          "age": "7",
          "weight": "9-4",
          "draw": "",
          "odds_str": "7/2",
          "odds_dec": 4.5,
          "silk_url": "https://images.timeform.com/silks/opt/00885098.png",
          "score": 41.5,
          "components": {
            "odds_value": 38.3,
            "recent_form": 52.0,
            "consistency": 25.0,
            "jockey": 60.0,
            "weight": 70.0,
            "absence_pen": 0.0,
            "going_factor": 0.92
          },
          "recommendation": {
            "type": "Skip",
            "confidence": 16,
            "label": "Skip",
            "reasoning": "moderate form; placed last time out"
          }
        },
        {
          "horse": "MUMAYAZ",
          "country": "IRE",
          "jockey": "Darragh Keenan",
          "trainer": "Tony Carroll",
          "form": "35746246",
          "age": "7",
          "weight": "9-1",
          "draw": "",
          "odds_str": "17/2",
          "odds_dec": 9.5,
          "silk_url": "https://images.timeform.com/silks/opt/00872039.png",
          "score": 36.4,
          "components": {
            "odds_value": 12.3,
            "recent_form": 44.3,
            "consistency": 25.0,
            "jockey": 60.0,
            "weight": 100.0,
            "absence_pen": 0.0,
            "going_factor": 0.92
          },
          "recommendation": {
            "type": "Skip",
            "confidence": 14,
            "label": "Skip",
            "reasoning": "moderate form"
          }
        },
        {
          "horse": "DARK SIDE THUNDER",
          "country": "GB",
          "jockey": "Oliver Stammers",
          "trainer": "Jessica Macey",
          "form": "5710-4892",
          "age": "7",
          "weight": "9-3",
          "draw": "",
          "odds_str": "7/1",
          "odds_dec": 8.0,
          "silk_url": "https://images.timeform.com/silks/opt/00006916.png",
          "score": 33.8,
          "components": {
            "odds_value": 16.7,
            "recent_form": 38.7,
            "consistency": 25.0,
            "jockey": 60.0,
            "weight": 80.0,
            "absence_pen": 0.0,
            "going_factor": 0.92
          },
          "recommendation": {
            "type": "Skip",
            "confidence": 13,
            "label": "Skip",
            "reasoning": "moderate form; placed last time out"
          }
        },
        {
          "horse": "INVINCIBLE SPEED",
          "country": "IRE",
          "jockey": "Jack Callan",
          "trainer": "Mark Loughnane",
          "form": "6964-1444",
          "age": "5",
          "weight": "9-5",
          "draw": "",
          "odds_str": "11/1",
          "odds_dec": 999.0,
          "silk_url": "https://images.timeform.com/silks/opt/00883534A.png",
          "score": 31.3,
          "components": {
            "odds_value": 0,
            "recent_form": 56.7,
            "consistency": 12.5,
            "jockey": 60.0,
            "weight": 60.0,
            "absence_pen": 0.0,
            "going_factor": 0.92
          },
          "recommendation": {
            "type": "Skip",
            "confidence": 12,
            "label": "Skip",
            "reasoning": "solid recent form"
          }
        }
      ]
    },
    {
      "id": "warwick-1837",
      "course": "Warwick",
      "time": "18:37",
      "title": "Subscribe To Head In Front Betting Handicap Hurdle",
      "distance": "3m 1f",
      "going": "Good to Firm",
      "race_class": "",
      "prize": "",
      "num_runners": 8,
      "ew_places": 3,
      "date": "2026-05-09",
      "runners": [
        {
          "horse": "SILVER GALE",
          "country": "IRE",
          "jockey": "Gavin Sheehan",
          "trainer": "Katy Price",
          "form": "870032-",
          "age": "5",
          "weight": "10-9",
          "draw": "",
          "odds_str": "11/4",
          "odds_dec": 3.75,
          "silk_url": "https://images.timeform.com/silks/opt/00888401.png",
          "score": 56.1,
          "components": {
            "odds_value": 67.9,
            "recent_form": 49.0,
            "consistency": 33.3,
            "jockey": 60.0,
            "weight": 79.2,
            "absence_pen": 0.0,
            "going_factor": 1.05
          },
          "recommendation": {
            "type": "EachWay",
            "confidence": 56,
            "label": "Each Way (Speculative)",
            "reasoning": "moderate form; placed last time out"
          }
        },
        {
          "horse": "BLUE IN THE WEST",
          "country": "IRE",
          "jockey": "Shane Quinlan",
          "trainer": "Ben Lund",
          "form": "74632P12-",
          "age": "9",
          "weight": "12-0",
          "draw": "",
          "odds_str": "9/2",
          "odds_dec": 5.5,
          "silk_url": "https://images.timeform.com/silks/opt/00868607.png",
          "score": 48.9,
          "components": {
            "odds_value": 42.8,
            "recent_form": 68.3,
            "consistency": 41.0,
            "jockey": 60.0,
            "weight": 0.0,
            "absence_pen": 0.0,
            "going_factor": 1.05
          },
          "recommendation": {
            "type": "Skip",
            "confidence": 19,
            "label": "Skip",
            "reasoning": "solid recent form; placed last time out; consistent placer (50% placed)"
          }
        },
        {
          "horse": "KANTAGUA DU LARGE",
          "country": "FR",
          "jockey": "Harry Cobden",
          "trainer": "Clive Boultbee-Brooks",
          "form": "737/56446-",
          "age": "6",
          "weight": "11-10",
          "draw": "",
          "odds_str": "2/1",
          "odds_dec": 3.0,
          "silk_url": "https://images.timeform.com/silks/opt/00871773.png",
          "score": 34.9,
          "components": {
            "odds_value": 87.7,
            "recent_form": 37.7,
            "consistency": 0,
            "jockey": 88.0,
            "weight": 16.7,
            "absence_pen": 15.0,
            "going_factor": 1.05
          },
          "recommendation": {
            "type": "Skip",
            "confidence": 13,
            "label": "Skip",
            "reasoning": "moderate form; returning from long absence"
          }
        },
        {
          "horse": "MEXICAN STAN",
          "country": "GB",
          "jockey": "Tom Broughton",
          "trainer": "Alastair Ralph",
          "form": "0074/P45-",
          "age": "6",
          "weight": "11-5",
          "draw": "",
          "odds_str": "9/2",
          "odds_dec": 5.5,
          "silk_url": "https://images.timeform.com/silks/opt/00013063.png",
          "score": 20.5,
          "components": {
            "odds_value": 42.8,
            "recent_form": 36.7,
            "consistency": 0,
            "jockey": 60.0,
            "weight": 37.5,
            "absence_pen": 15.0,
            "going_factor": 1.05
          },
          "recommendation": {
            "type": "Skip",
            "confidence": 8,
            "label": "Skip",
            "reasoning": "moderate form; returning from long absence; notable non-completion rate (33%)"
          }
        },
        {
          "horse": "BROADWAY HONEY",
          "country": "IRE",
          "jockey": "James Turner",
          "trainer": "Nigel & Willy Twiston-Davies",
          "form": "8/53355-",
          "age": "6",
          "weight": "11-10",
          "draw": "",
          "odds_str": "12/1",
          "odds_dec": 13.0,
          "silk_url": "https://images.timeform.com/silks/opt/00863720.png",
          "score": 20.2,
          "components": {
            "odds_value": 11.7,
            "recent_form": 48.3,
            "consistency": 40.0,
            "jockey": 60.0,
            "weight": 16.7,
            "absence_pen": 15.0,
            "going_factor": 1.05
          },
          "recommendation": {
            "type": "Skip",
            "confidence": 8,
            "label": "Skip",
            "reasoning": "moderate form; returning from long absence"
          }
        },
        {
          "horse": "KINGSTON KID",
          "country": "IRE",
          "jockey": "Tabitha Worsley",
          "trainer": "Georgie Howell",
          "form": "4P/755-",
          "age": "9",
          "weight": "10-8",
          "draw": "",
          "odds_str": "40/1",
          "odds_dec": 999.0,
          "silk_url": "https://images.timeform.com/silks/opt/00078253.png",
          "score": 14.1,
          "components": {
            "odds_value": 0,
            "recent_form": 37.5,
            "consistency": 0,
            "jockey": 60.0,
            "weight": 83.3,
            "absence_pen": 15.0,
            "going_factor": 1.05
          },
          "recommendation": {
            "type": "Skip",
            "confidence": 5,
            "label": "Skip",
            "reasoning": "moderate form; returning from long absence"
          }
        },
        {
          "horse": "ANNIES GOLD",
          "country": "GB",
          "jockey": "Murray Dodd",
          "trainer": "Nick Kent",
          "form": "0653/6PP5-",
          "age": "7",
          "weight": "10-4",
          "draw": "",
          "odds_str": "16/1",
          "odds_dec": 999.0,
          "silk_url": "https://images.timeform.com/silks/opt/00006309.png",
          "score": 9.8,
          "components": {
            "odds_value": 0,
            "recent_form": 18.5,
            "consistency": 0,
            "jockey": 60.0,
            "weight": 100.0,
            "absence_pen": 15.0,
            "going_factor": 1.05
          },
          "recommendation": {
            "type": "Skip",
            "confidence": 5,
            "label": "Skip",
            "reasoning": "poor recent form; returning from long absence; notable non-completion rate (50%)"
          }
        },
        {
          "horse": "DANGER NAP",
          "country": "IRE",
          "jockey": "Lorcan Williams",
          "trainer": "Jonjo & A.J. O'Neill",
          "form": "250/6P4-",
          "age": "5",
          "weight": "11-12",
          "draw": "",
          "odds_str": "10/1",
          "odds_dec": 11.0,
          "silk_url": "https://images.timeform.com/silks/opt/00065162.png",
          "score": 8.1,
          "components": {
            "odds_value": 15.8,
            "recent_form": 29.2,
            "consistency": 0,
            "jockey": 60.0,
            "weight": 8.3,
            "absence_pen": 15.0,
            "going_factor": 1.05
          },
          "recommendation": {
            "type": "Skip",
            "confidence": 5,
            "label": "Skip",
            "reasoning": "poor recent form; returning from long absence; notable non-completion rate (33%)"
          }
        }
      ]
    },
    {
      "id": "hexham-1847",
      "course": "Hexham",
      "time": "18:47",
      "title": "Jennis Justatenner 50Th Celebrations Handicap Hurdle",
      "distance": "2m",
      "going": "Good to Firm",
      "race_class": "",
      "prize": "",
      "num_runners": 10,
      "ew_places": 3,
      "date": "2026-05-09",
      "runners": [
        {
          "horse": "BREADALBANE LASS",
          "country": "GB",
          "jockey": "Toby Wynne",
          "trainer": "R. Mike Smith",
          "form": "25/066641-",
          "age": "6",
          "weight": "10-11",
          "draw": "",
          "odds_str": "11/4",
          "odds_dec": 3.75,
          "silk_url": "https://images.timeform.com/silks/opt/00017988.png",
          "score": 46.9,
          "components": {
            "odds_value": 87.7,
            "recent_form": 65.2,
            "consistency": 16.7,
            "jockey": 60.0,
            "weight": 68.0,
            "absence_pen": 15.0,
            "going_factor": 1.05
          },
          "recommendation": {
            "type": "Skip",
            "confidence": 18,
            "label": "Skip",
            "reasoning": "solid recent form; won last time out; returning from long absence"
          }
        },
        {
          "horse": "THE BEST WAY",
          "country": "FR",
          "jockey": "Danny McMenamin",
          "trainer": "Nicky Richards",
          "form": "P1/",
          "age": "8",
          "weight": "11-7",
          "draw": "",
          "odds_str": "16/5",
          "odds_dec": 4.2,
          "silk_url": "https://images.timeform.com/silks/opt/00873101.png",
          "score": 45.3,
          "components": {
            "odds_value": 77.1,
            "recent_form": 40.0,
            "consistency": 0,
            "jockey": 60.0,
            "weight": 28.0,
            "absence_pen": 0.0,
            "going_factor": 1.05
          },
          "recommendation": {
            "type": "Skip",
            "confidence": 18,
            "label": "Skip",
            "reasoning": "moderate form"
          }
        },
        {
          "horse": "NATIONAL QUESTION",
          "country": "IRE",
          "jockey": "Joshua Thompson",
          "trainer": "Adam Nicol",
          "form": "51251516-",
          "age": "6",
          "weight": "11-2",
          "draw": "",
          "odds_str": "6/1",
          "odds_dec": 999.0,
          "silk_url": "https://images.timeform.com/silks/opt/00869404.png",
          "score": 41.0,
          "components": {
            "odds_value": 0,
            "recent_form": 59.0,
            "consistency": 50.0,
            "jockey": 60.0,
            "weight": 48.0,
            "absence_pen": 0.0,
            "going_factor": 1.05
          },
          "recommendation": {
            "type": "Skip",
            "confidence": 16,
            "label": "Skip",
            "reasoning": "solid recent form; consistent placer (50% placed)"
          }
        },
        {
          "horse": "SNAPAUDACIAHEROS",
          "country": "IRE",
          "jockey": "Charlie Maggs",
          "trainer": "Rebecca Menzies",
          "form": "75/745851-",
          "age": "6",
          "weight": "10-9",
          "draw": "",
          "odds_str": "5/1",
          "odds_dec": 6.0,
          "silk_url": "https://images.timeform.com/silks/opt/00861102A.png",
          "score": 37.3,
          "components": {
            "odds_value": 50.6,
            "recent_form": 62.9,
            "consistency": 16.7,
            "jockey": 60.0,
            "weight": 76.0,
            "absence_pen": 15.0,
            "going_factor": 1.05
          },
          "recommendation": {
            "type": "Skip",
            "confidence": 14,
            "label": "Skip",
            "reasoning": "moderate form; won last time out; returning from long absence"
          }
        },
        {
          "horse": "TWO AULD PALS",
          "country": "IRE",
          "jockey": "Gregor Walkingshaw",
          "trainer": "Lucinda Russell & Michael Scudamore",
          "form": "65/3638-",
          "age": "8",
          "weight": "12-0",
          "draw": "",
          "odds_str": "11/2",
          "odds_dec": 6.5,
          "silk_url": "https://images.timeform.com/silks/opt/00001893.png",
          "score": 24.9,
          "components": {
            "odds_value": 45.9,
            "recent_form": 35.0,
            "consistency": 50.0,
            "jockey": 60.0,
            "weight": 0.0,
            "absence_pen": 15.0,
            "going_factor": 1.05
          },
          "recommendation": {
            "type": "Skip",
            "confidence": 9,
            "label": "Skip",
            "reasoning": "moderate form; consistent placer (50% placed); returning from long absence"
          }
        },
        {
          "horse": "MORNINGTON BEACH",
          "country": "IRE",
          "jockey": "Jonathon Bewley",
          "trainer": "George Bewley",
          "form": "5P72P-",
          "age": "6",
          "weight": "11-12",
          "draw": "",
          "odds_str": "16/1",
          "odds_dec": 17.0,
          "silk_url": "https://images.timeform.com/silks/opt/00844648.png",
          "score": 21.0,
          "components": {
            "odds_value": 10.7,
            "recent_form": 20.3,
            "consistency": 8.0,
            "jockey": 60.0,
            "weight": 8.0,
            "absence_pen": 0.0,
            "going_factor": 1.05
          },
          "recommendation": {
            "type": "Skip",
            "confidence": 8,
            "label": "Skip",
            "reasoning": "poor recent form; did not finish last time; notable non-completion rate (40%)"
          }
        },
        {
          "horse": "MY MY MY DELILAH",
          "country": "GB",
          "jockey": "Jamie Hamilton",
          "trainer": "Stuart Coltherd",
          "form": "2/6534U94-",
          "age": "6",
          "weight": "11-1",
          "draw": "",
          "odds_str": "7/1",
          "odds_dec": 8.0,
          "silk_url": "https://images.timeform.com/silks/opt/00012096.png",
          "score": 19.7,
          "components": {
            "odds_value": 35.2,
            "recent_form": 30.3,
            "consistency": 11.3,
            "jockey": 60.0,
            "weight": 52.0,
            "absence_pen": 15.0,
            "going_factor": 1.05
          },
          "recommendation": {
            "type": "Skip",
            "confidence": 7,
            "label": "Skip",
            "reasoning": "poor recent form; returning from long absence"
          }
        },
        {
          "horse": "JUSTLIKEFIRE",
          "country": "GB",
          "jockey": "Sean Quinlan",
          "trainer": "Jennie Candlish",
          "form": "90/4P2F-",
          "age": "7",
          "weight": "11-11",
          "draw": "",
          "odds_str": "13/2",
          "odds_dec": 7.5,
          "silk_url": "https://images.timeform.com/silks/opt/00872554.png",
          "score": 12.6,
          "components": {
            "odds_value": 38.3,
            "recent_form": 20.3,
            "consistency": 6.2,
            "jockey": 60.0,
            "weight": 12.0,
            "absence_pen": 15.0,
            "going_factor": 1.05
          },
          "recommendation": {
            "type": "Skip",
            "confidence": 5,
            "label": "Skip",
            "reasoning": "poor recent form; did not finish last time; returning from long absence; notable non-completion rate (50%)"
          }
        },
        {
          "horse": "HOURLESS",
          "country": "GB",
          "jockey": "Mr John Dixon",
          "trainer": "John Dixon",
          "form": "3/6468458-",
          "age": "6",
          "weight": "11-3",
          "draw": "",
          "odds_str": "9/2",
          "odds_dec": 999.0,
          "silk_url": "https://images.timeform.com/silks/opt/00013851.png",
          "score": 6.9,
          "components": {
            "odds_value": 0,
            "recent_form": 27.0,
            "consistency": 0,
            "jockey": 60.0,
            "weight": 44.0,
            "absence_pen": 15.0,
            "going_factor": 1.05
          },
          "recommendation": {
            "type": "Skip",
            "confidence": 5,
            "label": "Skip",
            "reasoning": "poor recent form; returning from long absence"
          }
        },
        {
          "horse": "MYTHICAL",
          "country": "FR",
          "jockey": "Joe Williamson",
          "trainer": "Samantha & Jacqueline Coward",
          "form": "7PP7/P-",
          "age": "9",
          "weight": "10-3",
          "draw": "",
          "odds_str": "80/1",
          "odds_dec": 81.0,
          "silk_url": "https://images.timeform.com/silks/opt/00006404.png",
          "score": 5.0,
          "components": {
            "odds_value": 0,
            "recent_form": 0.0,
            "consistency": 0,
            "jockey": 60.0,
            "weight": 100.0,
            "absence_pen": 15.0,
            "going_factor": 1.05
          },
          "recommendation": {
            "type": "Skip",
            "confidence": 5,
            "label": "Skip",
            "reasoning": "poor recent form; did not finish last time; returning from long absence; notable non-completion rate (100%)"
          }
        }
      ]
    },
    {
      "id": "leicester-1855",
      "course": "Leicester",
      "time": "18:55",
      "title": "Best Ticket Deals Online At Leicester Racecoursecouk Handicap",
      "distance": "1m 3f",
      "going": "Soft",
      "race_class": "",
      "prize": "",
      "num_runners": 6,
      "ew_places": 2,
      "date": "2026-05-09",
      "runners": [
        {
          "horse": "TROJAN TRUTH",
          "country": "GB",
          "jockey": "Owen Lewis",
          "trainer": "Ed de Giles",
          "form": "44111523-",
          "age": "7",
          "weight": "9-2",
          "draw": "",
          "odds_str": "20/1",
          "odds_dec": 21.0,
          "silk_url": "https://images.timeform.com/silks/opt/00844060.png",
          "score": 46.1,
          "components": {
            "odds_value": 0,
            "recent_form": 71.0,
            "consistency": 62.5,
            "jockey": 60.0,
            "weight": 100.0,
            "absence_pen": 0.0,
            "going_factor": 0.92
          },
          "recommendation": {
            "type": "Skip",
            "confidence": 18,
            "label": "Skip",
            "reasoning": "solid recent form; consistent placer (62% placed)"
          }
        },
        {
          "horse": "SWORD OF WESSEX",
          "country": "IRE",
          "jockey": "Luke Morris",
          "trainer": "James Owen",
          "form": "625-65581",
          "age": "4",
          "weight": "9-10",
          "draw": "",
          "odds_str": "5/2",
          "odds_dec": 3.5,
          "silk_url": "https://images.timeform.com/silks/opt/00889062.png",
          "score": 39.6,
          "components": {
            "odds_value": 52.4,
            "recent_form": 58.6,
            "consistency": 25.0,
            "jockey": 60.0,
            "weight": 0.0,
            "absence_pen": 0.0,
            "going_factor": 0.92
          },
          "recommendation": {
            "type": "Skip",
            "confidence": 15,
            "label": "Skip",
            "reasoning": "moderate form; won last time out"
          }
        },
        {
          "horse": "KURIOS LADY",
          "country": "GB",
          "jockey": "Rowan Scott",
          "trainer": "James Tate",
          "form": "6-3462",
          "age": "4",
          "weight": "9-8",
          "draw": "",
          "odds_str": "7/2",
          "odds_dec": 4.5,
          "silk_url": "https://images.timeform.com/silks/opt/00847926.png",
          "score": 39.5,
          "components": {
            "odds_value": 38.3,
            "recent_form": 53.7,
            "consistency": 40.0,
            "jockey": 60.0,
            "weight": 25.0,
            "absence_pen": 0.0,
            "going_factor": 0.92
          },
          "recommendation": {
            "type": "Skip",
            "confidence": 15,
            "label": "Skip",
            "reasoning": "moderate form; placed last time out"
          }
        },
        {
          "horse": "IWANTMYTIMEWITHYOU",
          "country": "GB",
          "jockey": "Mason Paetel",
          "trainer": "Ed Dunlop",
          "form": "411557-25",
          "age": "4",
          "weight": "9-4",
          "draw": "",
          "odds_str": "13/2",
          "odds_dec": 7.5,
          "silk_url": "https://images.timeform.com/silks/opt/00849388.png",
          "score": 38.0,
          "components": {
            "odds_value": 18.5,
            "recent_form": 47.7,
            "consistency": 37.5,
            "jockey": 60.0,
            "weight": 75.0,
            "absence_pen": 0.0,
            "going_factor": 0.92
          },
          "recommendation": {
            "type": "Skip",
            "confidence": 15,
            "label": "Skip",
            "reasoning": "moderate form"
          }
        },
        {
          "horse": "JOHN GALT",
          "country": "FR",
          "jockey": "Jack Callan",
          "trainer": "Jamie Osborne",
          "form": "4-44532",
          "age": "4",
          "weight": "9-9",
          "draw": "",
          "odds_str": "13/2",
          "odds_dec": 7.5,
          "silk_url": "https://images.timeform.com/silks/opt/00863718.png",
          "score": 35.1,
          "components": {
            "odds_value": 18.5,
            "recent_form": 62.0,
            "consistency": 33.3,
            "jockey": 60.0,
            "weight": 12.5,
            "absence_pen": 0.0,
            "going_factor": 0.92
          },
          "recommendation": {
            "type": "Skip",
            "confidence": 14,
            "label": "Skip",
            "reasoning": "solid recent form; placed last time out"
          }
        },
        {
          "horse": "JOHNNY BOOM",
          "country": "IRE",
          "jockey": "Gina Mangan",
          "trainer": "Shaun Lycett",
          "form": "4659/1-762",
          "age": "8",
          "weight": "9-7",
          "draw": "",
          "odds_str": "5/2",
          "odds_dec": 3.5,
          "silk_url": "https://images.timeform.com/silks/opt/00831048.png",
          "score": 31.8,
          "components": {
            "odds_value": 52.4,
            "recent_form": 54.5,
            "consistency": 50.0,
            "jockey": 60.0,
            "weight": 37.5,
            "absence_pen": 15.0,
            "going_factor": 0.92
          },
          "recommendation": {
            "type": "Skip",
            "confidence": 12,
            "label": "Skip",
            "reasoning": "moderate form; placed last time out; consistent placer (50% placed); returning from long absence"
          }
        }
      ]
    },
    {
      "id": "warwick-1907",
      "course": "Warwick",
      "time": "19:07",
      "title": "Lewis Badges 1832 Handicap Hurdle",
      "distance": "2m 5f",
      "going": "Good to Firm",
      "race_class": "",
      "prize": "",
      "num_runners": 8,
      "ew_places": 3,
      "date": "2026-05-09",
      "runners": [
        {
          "horse": "THREE PIKES",
          "country": "GB",
          "jockey": "Oscar Palmer",
          "trainer": "Henry Oliver",
          "form": "52/122341-",
          "age": "6",
          "weight": "11-11",
          "draw": "",
          "odds_str": "15/8",
          "odds_dec": 2.88,
          "silk_url": "https://images.timeform.com/silks/opt/00018532.png",
          "score": 60.7,
          "components": {
            "odds_value": 91.8,
            "recent_form": 87.1,
            "consistency": 83.3,
            "jockey": 60.0,
            "weight": 20.8,
            "absence_pen": 15.0,
            "going_factor": 1.05
          },
          "recommendation": {
            "type": "Win",
            "confidence": 60,
            "label": "Win Bet",
            "reasoning": "strong recent form; won last time out; consistent placer (83% placed); returning from long absence; short price reflects market confidence"
          }
        },
        {
          "horse": "KOM TU VOUDRAS",
          "country": "FR",
          "jockey": "Harry Cobden",
          "trainer": "Faye Bramley",
          "form": "P/301-",
          "age": "6",
          "weight": "11-10",
          "draw": "",
          "odds_str": "9/2",
          "odds_dec": 5.5,
          "silk_url": "https://images.timeform.com/silks/opt/00032184.png",
          "score": 45.8,
          "components": {
            "odds_value": 42.8,
            "recent_form": 73.8,
            "consistency": 66.7,
            "jockey": 88.0,
            "weight": 25.0,
            "absence_pen": 15.0,
            "going_factor": 1.05
          },
          "recommendation": {
            "type": "Skip",
            "confidence": 18,
            "label": "Skip",
            "reasoning": "solid recent form; won last time out; consistent placer (66% placed); returning from long absence"
          }
        },
        {
          "horse": "IMPECUNIOUS",
          "country": "IRE",
          "jockey": "Bryan Carver",
          "trainer": "Ian Chanin",
          "form": "50013/421-",
          "age": "7",
          "weight": "11-12",
          "draw": "",
          "odds_str": "10/1",
          "odds_dec": 11.0,
          "silk_url": "https://images.timeform.com/silks/opt/00044734.png",
          "score": 41.9,
          "components": {
            "odds_value": 15.8,
            "recent_form": 97.7,
            "consistency": 66.7,
            "jockey": 65.0,
            "weight": 16.7,
            "absence_pen": 15.0,
            "going_factor": 1.05
          },
          "recommendation": {
            "type": "Skip",
            "confidence": 16,
            "label": "Skip",
            "reasoning": "strong recent form; won last time out; consistent placer (66% placed); returning from long absence"
          }
        },
        {
          "horse": "CAMARRATE",
          "country": "IRE",
          "jockey": "William Maggs",
          "trainer": "Donald McCain",
          "form": "503/20361-",
          "age": "6",
          "weight": "11-8",
          "draw": "",
          "odds_str": "9/2",
          "odds_dec": 5.5,
          "silk_url": "https://images.timeform.com/silks/opt/00881851.png",
          "score": 39.6,
          "components": {
            "odds_value": 42.8,
            "recent_form": 68.7,
            "consistency": 60.0,
            "jockey": 60.0,
            "weight": 33.3,
            "absence_pen": 15.0,
            "going_factor": 1.05
          },
          "recommendation": {
            "type": "Skip",
            "confidence": 15,
            "label": "Skip",
            "reasoning": "solid recent form; won last time out; consistent placer (60% placed); returning from long absence"
          }
        },
        {
          "horse": "IL VA DE SOI",
          "country": "FR",
          "jockey": "Paul O'Brien",
          "trainer": "Harry Derham",
          "form": "3FP0P758-",
          "age": "8",
          "weight": "11-7",
          "draw": "",
          "odds_str": "17/2",
          "odds_dec": 9.5,
          "silk_url": "https://images.timeform.com/silks/opt/00876524.png",
          "score": 27.7,
          "components": {
            "odds_value": 20.1,
            "recent_form": 19.7,
            "consistency": 5.4,
            "jockey": 72.0,
            "weight": 37.5,
            "absence_pen": 0.0,
            "going_factor": 1.05
          },
          "recommendation": {
            "type": "Skip",
            "confidence": 11,
            "label": "Skip",
            "reasoning": "poor recent form; notable non-completion rate (38%)"
          }
        },
        {
          "horse": "URBAN ISLE",
          "country": "GB",
          "jockey": "Isabelle Ryder",
          "trainer": "Hughie Morrison",
          "form": "783/5876-",
          "age": "5",
          "weight": "10-6",
          "draw": "",
          "odds_str": "6/1",
          "odds_dec": 7.0,
          "silk_url": "https://images.timeform.com/silks/opt/00844005.png",
          "score": 19.5,
          "components": {
            "odds_value": 31.2,
            "recent_form": 23.5,
            "consistency": 0,
            "jockey": 60.0,
            "weight": 100.0,
            "absence_pen": 15.0,
            "going_factor": 1.05
          },
          "recommendation": {
            "type": "Skip",
            "confidence": 7,
            "label": "Skip",
            "reasoning": "poor recent form; returning from long absence"
          }
        },
        {
          "horse": "MAMMIES BOY",
          "country": "IRE",
          "jockey": "Caoilin Quinn",
          "trainer": "Nick Scholfield",
          "form": "14/107U3-",
          "age": "8",
          "weight": "11-13",
          "draw": "",
          "odds_str": "12/1",
          "odds_dec": 999.0,
          "silk_url": "https://images.timeform.com/silks/opt/00876389.png",
          "score": 11.8,
          "components": {
            "odds_value": 0,
            "recent_form": 34.7,
            "consistency": 28.0,
            "jockey": 68.0,
            "weight": 12.5,
            "absence_pen": 15.0,
            "going_factor": 1.05
          },
          "recommendation": {
            "type": "Skip",
            "confidence": 5,
            "label": "Skip",
            "reasoning": "poor recent form; returning from long absence"
          }
        },
        {
          "horse": "GWASH",
          "country": "IRE",
          "jockey": "Tom Broughton",
          "trainer": "Fergal O'Brien",
          "form": "45/662876-",
          "age": "7",
          "weight": "12-2",
          "draw": "",
          "odds_str": "14/1",
          "odds_dec": 15.0,
          "silk_url": "https://images.timeform.com/silks/opt/00883404.png",
          "score": 8.1,
          "components": {
            "odds_value": 8.6,
            "recent_form": 29.3,
            "consistency": 16.7,
            "jockey": 60.0,
            "weight": 0.0,
            "absence_pen": 15.0,
            "going_factor": 1.05
          },
          "recommendation": {
            "type": "Skip",
            "confidence": 5,
            "label": "Skip",
            "reasoning": "poor recent form; returning from long absence"
          }
        }
      ]
    },
    {
      "id": "leicester-1925",
      "course": "Leicester",
      "time": "19:25",
      "title": "Heather Small Plays Leicester Races 4Th July Handicap",
      "distance": "7f",
      "going": "Soft",
      "race_class": "",
      "prize": "",
      "num_runners": 9,
      "ew_places": 3,
      "date": "2026-05-09",
      "runners": [
        {
          "horse": "FENLANDER",
          "country": "GB",
          "jockey": "Kieran O'Neill",
          "trainer": "Pam Sly",
          "form": "335623-23",
          "age": "5",
          "weight": "9-0",
          "draw": "",
          "odds_str": "11/2",
          "odds_dec": 6.5,
          "silk_url": "https://images.timeform.com/silks/opt/00080036.png",
          "score": 54.8,
          "components": {
            "odds_value": 40.2,
            "recent_form": 68.3,
            "consistency": 75.0,
            "jockey": 60.0,
            "weight": 85.0,
            "absence_pen": 0.0,
            "going_factor": 0.92
          },
          "recommendation": {
            "type": "EachWay",
            "confidence": 54,
            "label": "Each Way (Speculative)",
            "reasoning": "solid recent form; consistent placer (75% placed)"
          }
        },
        {
          "horse": "TATTIE BOGLE",
          "country": "GB",
          "jockey": "Jack Callan",
          "trainer": "Charlie Johnston",
          "form": "373-42531",
          "age": "4",
          "weight": "9-7",
          "draw": "",
          "odds_str": "11/2",
          "odds_dec": 6.5,
          "silk_url": "https://images.timeform.com/silks/opt/00849717.png",
          "score": 53.8,
          "components": {
            "odds_value": 40.2,
            "recent_form": 83.6,
            "consistency": 62.5,
            "jockey": 60.0,
            "weight": 50.0,
            "absence_pen": 0.0,
            "going_factor": 0.92
          },
          "recommendation": {
            "type": "EachWay",
            "confidence": 53,
            "label": "Each Way (Speculative)",
            "reasoning": "solid recent form; won last time out; consistent placer (62% placed)"
          }
        },
        {
          "horse": "CALL GLORY",
          "country": "IRE",
          "jockey": "Ryan Kavanagh",
          "trainer": "Ian Williams",
          "form": "54326342",
          "age": "5",
          "weight": "8-11",
          "draw": "",
          "odds_str": "18/1",
          "odds_dec": 19.0,
          "silk_url": "https://images.timeform.com/silks/opt/00880520.png",
          "score": 43.3,
          "components": {
            "odds_value": 6.4,
            "recent_form": 61.7,
            "consistency": 50.0,
            "jockey": 60.0,
            "weight": 100.0,
            "absence_pen": 0.0,
            "going_factor": 0.92
          },
          "recommendation": {
            "type": "Skip",
            "confidence": 17,
            "label": "Skip",
            "reasoning": "solid recent form; placed last time out; consistent placer (50% placed)"
          }
        },
        {
          "horse": "ZUBARU",
          "country": "GB",
          "jockey": "Darragh Keenan",
          "trainer": "George Scott",
          "form": "2/25485-31",
          "age": "4",
          "weight": "10-3",
          "draw": "",
          "odds_str": "6/4",
          "odds_dec": 2.5,
          "silk_url": "https://images.timeform.com/silks/opt/00885809.png",
          "score": 43.1,
          "components": {
            "odds_value": 100,
            "recent_form": 72.8,
            "consistency": 42.9,
            "jockey": 60.0,
            "weight": 0.0,
            "absence_pen": 15.0,
            "going_factor": 0.92
          },
          "recommendation": {
            "type": "Skip",
            "confidence": 17,
            "label": "Skip",
            "reasoning": "solid recent form; won last time out; returning from long absence"
          }
        },
        {
          "horse": "AL HOFZAN",
          "country": "IRE",
          "jockey": "Gina Mangan",
          "trainer": "Georgina Nicholls",
          "form": "23-304235",
          "age": "4",
          "weight": "9-5",
          "draw": "",
          "odds_str": "22/1",
          "odds_dec": 23.0,
          "silk_url": "https://images.timeform.com/silks/opt/00884191.png",
          "score": 38.2,
          "components": {
            "odds_value": 3.4,
            "recent_form": 54.0,
            "consistency": 62.5,
            "jockey": 60.0,
            "weight": 60.0,
            "absence_pen": 0.0,
            "going_factor": 0.92
          },
          "recommendation": {
            "type": "Skip",
            "confidence": 15,
            "label": "Skip",
            "reasoning": "moderate form; consistent placer (62% placed)"
          }
        },
        {
          "horse": "ENPASSANT",
          "country": "IRE",
          "jockey": "David Nolan",
          "trainer": "Michael Herrington",
          "form": "5-5240917",
          "age": "5",
          "weight": "9-4",
          "draw": "",
          "odds_str": "18/1",
          "odds_dec": 19.0,
          "silk_url": "https://images.timeform.com/silks/opt/00888706.png",
          "score": 30.8,
          "components": {
            "odds_value": 6.4,
            "recent_form": 41.7,
            "consistency": 25.0,
            "jockey": 60.0,
            "weight": 65.0,
            "absence_pen": 0.0,
            "going_factor": 0.92
          },
          "recommendation": {
            "type": "Skip",
            "confidence": 12,
            "label": "Skip",
            "reasoning": "moderate form"
          }
        },
        {
          "horse": "TEX",
          "country": "FR",
          "jockey": "Jack Dace",
          "trainer": "George Baker",
          "form": "642/44333-",
          "age": "5",
          "weight": "9-6",
          "draw": "",
          "odds_str": "9/1",
          "odds_dec": 10.0,
          "silk_url": "https://images.timeform.com/silks/opt/00885052A.png",
          "score": 30.1,
          "components": {
            "odds_value": 22.2,
            "recent_form": 62.0,
            "consistency": 60.0,
            "jockey": 60.0,
            "weight": 55.0,
            "absence_pen": 15.0,
            "going_factor": 0.92
          },
          "recommendation": {
            "type": "Skip",
            "confidence": 12,
            "label": "Skip",
            "reasoning": "solid recent form; consistent placer (60% placed); returning from long absence"
          }
        },
        {
          "horse": "CYPRIOT DIASPORA",
          "country": "GB",
          "jockey": "Oliver Searle",
          "trainer": "Rod Millman",
          "form": "2411006-5",
          "age": "5",
          "weight": "9-7",
          "draw": "",
          "odds_str": "30/1",
          "odds_dec": 31.0,
          "silk_url": "https://images.timeform.com/silks/opt/00845667.png",
          "score": 26.3,
          "components": {
            "odds_value": 0,
            "recent_form": 30.0,
            "consistency": 37.5,
            "jockey": 60.0,
            "weight": 50.0,
            "absence_pen": 0.0,
            "going_factor": 0.92
          },
          "recommendation": {
            "type": "Skip",
            "confidence": 10,
            "label": "Skip",
            "reasoning": "poor recent form"
          }
        },
        {
          "horse": "ALBESEEINGYER",
          "country": "GB",
          "jockey": "Rowan Scott",
          "trainer": "Steph Hollinshead",
          "form": "7/47308-02",
          "age": "7",
          "weight": "9-8",
          "draw": "",
          "odds_str": "5/1",
          "odds_dec": 6.0,
          "silk_url": "https://images.timeform.com/silks/opt/00013013.png",
          "score": 23.0,
          "components": {
            "odds_value": 44.4,
            "recent_form": 37.0,
            "consistency": 28.6,
            "jockey": 60.0,
            "weight": 45.0,
            "absence_pen": 15.0,
            "going_factor": 0.92
          },
          "recommendation": {
            "type": "Skip",
            "confidence": 9,
            "label": "Skip",
            "reasoning": "moderate form; placed last time out; returning from long absence"
          }
        }
      ]
    },
    {
      "id": "warwick-1937",
      "course": "Warwick",
      "time": "19:37",
      "title": "Jockey Club 0 110 Rated Series Final Open Hunters Chase",
      "distance": "3m",
      "going": "Good to Firm",
      "race_class": "",
      "prize": "",
      "num_runners": 4,
      "ew_places": 1,
      "date": "2026-05-09",
      "runners": [
        {
          "horse": "WALKIN OUT",
          "country": "GB",
          "jockey": "Miss Anna Johnston",
          "trainer": "L. Jefford",
          "form": "23/32-",
          "age": "9",
          "weight": "11-7",
          "draw": "",
          "odds_str": "5/2",
          "odds_dec": 3.5,
          "silk_url": "https://images.timeform.com/silks/opt/00877990.png",
          "score": 51.5,
          "components": {
            "odds_value": 31.2,
            "recent_form": 75.0,
            "consistency": 100.0,
            "jockey": 60.0,
            "weight": 100.0,
            "absence_pen": 15.0,
            "going_factor": 1.05
          },
          "recommendation": {
            "type": "Skip",
            "confidence": 20,
            "label": "Skip",
            "reasoning": "strong recent form; placed last time out; consistent placer (100% placed); returning from long absence"
          }
        },
        {
          "horse": "MALINAS GLORY",
          "country": "IRE",
          "jockey": "Miss Heidi Palin",
          "trainer": "Miss Hannah Lewis",
          "form": "PF41P700/",
          "age": "9",
          "weight": "12-0",
          "draw": "",
          "odds_str": "5/6",
          "odds_dec": 1.91,
          "silk_url": "https://images.timeform.com/silks/opt/00014998.png",
          "score": 42.7,
          "components": {
            "odds_value": 66.5,
            "recent_form": 40.0,
            "consistency": 0,
            "jockey": 60.0,
            "weight": 30.0,
            "absence_pen": 0.0,
            "going_factor": 1.05
          },
          "recommendation": {
            "type": "Skip",
            "confidence": 17,
            "label": "Skip",
            "reasoning": "moderate form"
          }
        },
        {
          "horse": "BEST MATE DAVE",
          "country": "GB",
          "jockey": "Mr Frederick Philipson-Stow",
          "trainer": "Oliver Edward Hayes",
          "form": "4P365P/3-",
          "age": "9",
          "weight": "12-0",
          "draw": "",
          "odds_str": "6/1",
          "odds_dec": 7.0,
          "silk_url": "https://images.timeform.com/silks/opt/00007633A.png",
          "score": 35.8,
          "components": {
            "odds_value": 10.1,
            "recent_form": 65.0,
            "consistency": 100.0,
            "jockey": 60.0,
            "weight": 30.0,
            "absence_pen": 15.0,
            "going_factor": 1.05
          },
          "recommendation": {
            "type": "Skip",
            "confidence": 14,
            "label": "Skip",
            "reasoning": "solid recent form; consistent placer (100% placed); returning from long absence"
          }
        },
        {
          "horse": "GOOD SOURCE",
          "country": "IRE",
          "jockey": "Miss Charlotte Butler",
          "trainer": "E. Turner",
          "form": "1/",
          "age": "9",
          "weight": "12-3",
          "draw": "",
          "odds_str": "8/1",
          "odds_dec": 9.0,
          "silk_url": "https://images.timeform.com/silks/opt/00007240.png",
          "score": 23.7,
          "components": {
            "odds_value": 5.3,
            "recent_form": 40.0,
            "consistency": 0,
            "jockey": 60.0,
            "weight": 0.0,
            "absence_pen": 0.0,
            "going_factor": 1.05
          },
          "recommendation": {
            "type": "Skip",
            "confidence": 9,
            "label": "Skip",
            "reasoning": "moderate form"
          }
        }
      ]
    },
    {
      "id": "leicester-1955",
      "course": "Leicester",
      "time": "19:55",
      "title": "Go West Plays Leicester Races 4Th July Handicap",
      "distance": "1m 2f",
      "going": "Soft",
      "race_class": "",
      "prize": "",
      "num_runners": 12,
      "ew_places": 4,
      "date": "2026-05-09",
      "runners": [
        {
          "horse": "OASIS SUNRISE",
          "country": "IRE",
          "jockey": "Jack Dace",
          "trainer": "Grace Harris",
          "form": "75662-521",
          "age": "4",
          "weight": "10-3",
          "draw": "",
          "odds_str": "5/1",
          "odds_dec": 6.0,
          "silk_url": "https://images.timeform.com/silks/opt/00888456.png",
          "score": 51.3,
          "components": {
            "odds_value": 63.0,
            "recent_form": 86.2,
            "consistency": 37.5,
            "jockey": 60.0,
            "weight": 0.0,
            "absence_pen": 0.0,
            "going_factor": 0.92
          },
          "recommendation": {
            "type": "EachWay",
            "confidence": 51,
            "label": "Each Way (Speculative)",
            "reasoning": "strong recent form; won last time out"
          }
        },
        {
          "horse": "VERSATILE",
          "country": "IRE",
          "jockey": "Luke Morris",
          "trainer": "James Owen",
          "form": "758-90866",
          "age": "5",
          "weight": "9-3",
          "draw": "",
          "odds_str": "3/1",
          "odds_dec": 4.0,
          "silk_url": "https://images.timeform.com/silks/opt/00882399.png",
          "score": 44.4,
          "components": {
            "odds_value": 100,
            "recent_form": 19.0,
            "consistency": 0,
            "jockey": 60.0,
            "weight": 82.4,
            "absence_pen": 0.0,
            "going_factor": 0.92
          },
          "recommendation": {
            "type": "Skip",
            "confidence": 17,
            "label": "Skip",
            "reasoning": "poor recent form"
          }
        },
        {
          "horse": "MYNA",
          "country": "IRE",
          "jockey": "William Carson",
          "trainer": "Tony Carroll",
          "form": "847-15236",
          "age": "5",
          "weight": "9-2",
          "draw": "",
          "odds_str": "10/1",
          "odds_dec": 11.0,
          "silk_url": "https://images.timeform.com/silks/opt/00888150.png",
          "score": 43.4,
          "components": {
            "odds_value": 29.3,
            "recent_form": 53.7,
            "consistency": 37.5,
            "jockey": 60.0,
            "weight": 88.2,
            "absence_pen": 0.0,
            "going_factor": 0.92
          },
          "recommendation": {
            "type": "Skip",
            "confidence": 17,
            "label": "Skip",
            "reasoning": "moderate form"
          }
        },
        {
          "horse": "CLIPSHAM NOBLE",
          "country": "IRE",
          "jockey": "Liam Wright",
          "trainer": "Charlie Clover",
          "form": "86065-465",
          "age": "4",
          "weight": "9-0 (8-13)",
          "draw": "",
          "odds_str": "9/1",
          "odds_dec": 10.0,
          "silk_url": "https://images.timeform.com/silks/opt/00854089.png",
          "score": 35.8,
          "components": {
            "odds_value": 33.3,
            "recent_form": 37.0,
            "consistency": 0,
            "jockey": 60.0,
            "weight": 100.0,
            "absence_pen": 0.0,
            "going_factor": 0.92
          },
          "recommendation": {
            "type": "Skip",
            "confidence": 14,
            "label": "Skip",
            "reasoning": "moderate form"
          }
        },
        {
          "horse": "FILLYFUDGE",
          "country": "GB",
          "jockey": "Darragh Keenan",
          "trainer": "Lemos De Souza",
          "form": "545305-67",
          "age": "7",
          "weight": "9-6",
          "draw": "",
          "odds_str": "15/2",
          "odds_dec": 8.5,
          "silk_url": "https://images.timeform.com/silks/opt/00080023.png",
          "score": 33.5,
          "components": {
            "odds_value": 41.2,
            "recent_form": 28.7,
            "consistency": 12.5,
            "jockey": 60.0,
            "weight": 64.7,
            "absence_pen": 0.0,
            "going_factor": 0.92
          },
          "recommendation": {
            "type": "Skip",
            "confidence": 13,
            "label": "Skip",
            "reasoning": "poor recent form"
          }
        },
        {
          "horse": "MOORETOWN LAD",
          "country": "IRE",
          "jockey": "Sean Dylan Bowen",
          "trainer": "Adrian Wintle",
          "form": "8/80-49474",
          "age": "6",
          "weight": "9-3",
          "draw": "",
          "odds_str": "7/2",
          "odds_dec": 4.5,
          "silk_url": "https://images.timeform.com/silks/opt/00870286.png",
          "score": 33.0,
          "components": {
            "odds_value": 87.7,
            "recent_form": 38.0,
            "consistency": 0,
            "jockey": 60.0,
            "weight": 82.4,
            "absence_pen": 15.0,
            "going_factor": 0.92
          },
          "recommendation": {
            "type": "Skip",
            "confidence": 13,
            "label": "Skip",
            "reasoning": "moderate form; returning from long absence"
          }
        },
        {
          "horse": "LUMINOUS APPROACH",
          "country": "IRE",
          "jockey": "Gina Mangan",
          "trainer": "Shaun Lycett",
          "form": "067-",
          "age": "4",
          "weight": "9-8",
          "draw": "",
          "odds_str": "6/1",
          "odds_dec": 7.0,
          "silk_url": "https://images.timeform.com/silks/opt/00870530.png",
          "score": 31.4,
          "components": {
            "odds_value": 52.4,
            "recent_form": 22.5,
            "consistency": 0,
            "jockey": 60.0,
            "weight": 52.9,
            "absence_pen": 0.0,
            "going_factor": 0.92
          },
          "recommendation": {
            "type": "Skip",
            "confidence": 12,
            "label": "Skip",
            "reasoning": "poor recent form"
          }
        },
        {
          "horse": "CITY ESCAPE",
          "country": "IRE",
          "jockey": "Kieran O'Neill",
          "trainer": "Nikki Evans",
          "form": "44424673-",
          "age": "9",
          "weight": "9-8",
          "draw": "",
          "odds_str": "30/1",
          "odds_dec": 31.0,
          "silk_url": "https://images.timeform.com/silks/opt/00047900.png",
          "score": 29.9,
          "components": {
            "odds_value": 3.2,
            "recent_form": 45.3,
            "consistency": 25.0,
            "jockey": 60.0,
            "weight": 52.9,
            "absence_pen": 0.0,
            "going_factor": 0.92
          },
          "recommendation": {
            "type": "Skip",
            "confidence": 11,
            "label": "Skip",
            "reasoning": "moderate form"
          }
        },
        {
          "horse": "PURE THEORY",
          "country": "GB",
          "jockey": "Ryan Kavanagh",
          "trainer": "Stephanie Cassidy",
          "form": "64-454690",
          "age": "4",
          "weight": "9-0 (8-13)",
          "draw": "",
          "odds_str": "33/1",
          "odds_dec": 34.0,
          "silk_url": "https://images.timeform.com/silks/opt/00022953.png",
          "score": 23.9,
          "components": {
            "odds_value": 2.0,
            "recent_form": 20.3,
            "consistency": 0,
            "jockey": 60.0,
            "weight": 100.0,
            "absence_pen": 0.0,
            "going_factor": 0.92
          },
          "recommendation": {
            "type": "Skip",
            "confidence": 9,
            "label": "Skip",
            "reasoning": "poor recent form"
          }
        },
        {
          "horse": "MAJESTIC LEO",
          "country": "IRE",
          "jockey": "Non Runner",
          "trainer": "Gary Brown",
          "form": "9589-0608",
          "age": "4",
          "weight": "9-4",
          "draw": "",
          "odds_str": "100/1",
          "odds_dec": 999.0,
          "silk_url": "https://images.timeform.com/silks/opt/00877927.png",
          "score": 19.1,
          "components": {
            "odds_value": 0,
            "recent_form": 13.0,
            "consistency": 0,
            "jockey": 60.0,
            "weight": 76.5,
            "absence_pen": 0.0,
            "going_factor": 0.92
          },
          "recommendation": {
            "type": "Skip",
            "confidence": 7,
            "label": "Skip",
            "reasoning": "poor recent form"
          }
        },
        {
          "horse": "GERT LUSH",
          "country": "IRE",
          "jockey": "Owen Lewis",
          "trainer": "Roger Teal",
          "form": "05350/7",
          "age": "9",
          "weight": "9-6",
          "draw": "",
          "odds_str": "22/1",
          "odds_dec": 23.0,
          "silk_url": "https://images.timeform.com/silks/opt/00082335.png",
          "score": 9.3,
          "components": {
            "odds_value": 8.2,
            "recent_form": 25.0,
            "consistency": 0,
            "jockey": 60.0,
            "weight": 64.7,
            "absence_pen": 15.0,
            "going_factor": 0.92
          },
          "recommendation": {
            "type": "Skip",
            "confidence": 5,
            "label": "Skip",
            "reasoning": "poor recent form; returning from long absence"
          }
        },
        {
          "horse": "EAGER PUCCINI",
          "country": "GB",
          "jockey": "Mason Paetel",
          "trainer": "Julia & Shelley Birkett",
          "form": "09/0700-6",
          "age": "4",
          "weight": "9-0 (8-13)",
          "draw": "",
          "odds_str": "66/1",
          "odds_dec": 67.0,
          "silk_url": "https://images.timeform.com/silks/opt/00885691.png",
          "score": 8.8,
          "components": {
            "odds_value": 0,
            "recent_form": 17.0,
            "consistency": 0,
            "jockey": 60.0,
            "weight": 100.0,
            "absence_pen": 15.0,
            "going_factor": 0.92
          },
          "recommendation": {
            "type": "Skip",
            "confidence": 5,
            "label": "Skip",
            "reasoning": "poor recent form; returning from long absence"
          }
        }
      ]
    },
    {
      "id": "warwick-2007",
      "course": "Warwick",
      "time": "20:07",
      "title": "Claverdon Fc Have Done The Double Open National Hunt Flat",
      "distance": "2m",
      "going": "Good to Firm",
      "race_class": "",
      "prize": "",
      "num_runners": 6,
      "ew_places": 2,
      "date": "2026-05-09",
      "runners": [
        {
          "horse": "LEGEND D&#39;AIRY",
          "country": "FR",
          "jockey": "Ben Jones",
          "trainer": "Ben Pauling",
          "form": "2-",
          "age": "5",
          "weight": "11-2",
          "draw": "",
          "odds_str": "8/13",
          "odds_dec": 1.62,
          "silk_url": "https://images.timeform.com/silks/opt/00890672.png",
          "score": 76.9,
          "components": {
            "odds_value": 100,
            "recent_form": 80.0,
            "consistency": 100.0,
            "jockey": 60.0,
            "weight": 0.0,
            "absence_pen": 0.0,
            "going_factor": 1.05
          },
          "recommendation": {
            "type": "Win",
            "confidence": 76,
            "label": "Strong Win Bet",
            "reasoning": "strong recent form; placed last time out; consistent placer (100% placed); short price reflects market confidence"
          }
        },
        {
          "horse": "NATE OF SPADES",
          "country": "IRE",
          "jockey": "Gavin Sheehan",
          "trainer": "Charlie Longsdon",
          "form": "",
          "age": "4",
          "weight": "10-10",
          "draw": "",
          "odds_str": "15/8",
          "odds_dec": 2.88,
          "silk_url": "https://images.timeform.com/silks/opt/00032921.png",
          "score": 49.6,
          "components": {
            "odds_value": 66.0,
            "recent_form": 40.0,
            "consistency": 0,
            "jockey": 60.0,
            "weight": 100.0,
            "absence_pen": 0.0,
            "going_factor": 1.05
          },
          "recommendation": {
            "type": "Skip",
            "confidence": 19,
            "label": "Skip",
            "reasoning": "moderate form"
          }
        },
        {
          "horse": "ROLL A DOLLAR",
          "country": "GB",
          "jockey": "Liam Harrison",
          "trainer": "David Brace",
          "form": "3-",
          "age": "5",
          "weight": "11-2",
          "draw": "",
          "odds_str": "16/1",
          "odds_dec": 17.0,
          "silk_url": "https://images.timeform.com/silks/opt/00892442.png",
          "score": 47.2,
          "components": {
            "odds_value": 2.0,
            "recent_form": 65.0,
            "consistency": 100.0,
            "jockey": 65.0,
            "weight": 0.0,
            "absence_pen": 0.0,
            "going_factor": 1.05
          },
          "recommendation": {
            "type": "Skip",
            "confidence": 18,
            "label": "Skip",
            "reasoning": "solid recent form; consistent placer (100% placed)"
          }
        },
        {
          "horse": "DENNIS&#39;S HONOR",
          "country": "GB",
          "jockey": "Paul O'Brien",
          "trainer": "Steph Hollinshead",
          "form": "",
          "age": "4",
          "weight": "10-10",
          "draw": "",
          "odds_str": "66/1",
          "odds_dec": 67.0,
          "silk_url": "https://images.timeform.com/silks/opt/00893099.png",
          "score": 34.2,
          "components": {
            "odds_value": 0,
            "recent_form": 40.0,
            "consistency": 0,
            "jockey": 72.0,
            "weight": 100.0,
            "absence_pen": 0.0,
            "going_factor": 1.05
          },
          "recommendation": {
            "type": "Skip",
            "confidence": 13,
            "label": "Skip",
            "reasoning": "moderate form"
          }
        },
        {
          "horse": "MIDNIGHT ESCAPE",
          "country": "GB",
          "jockey": "Jack Quinlan",
          "trainer": "Ben Case",
          "form": "4-",
          "age": "5",
          "weight": "11-2",
          "draw": "",
          "odds_str": "6/1",
          "odds_dec": 999.0,
          "silk_url": "https://images.timeform.com/silks/opt/00007898.png",
          "score": 25.5,
          "components": {
            "odds_value": 0,
            "recent_form": 50.0,
            "consistency": 0,
            "jockey": 60.0,
            "weight": 0.0,
            "absence_pen": 0.0,
            "going_factor": 1.05
          },
          "recommendation": {
            "type": "Skip",
            "confidence": 10,
            "label": "Skip",
            "reasoning": "moderate form"
          }
        },
        {
          "horse": "BARASCARIA TEN",
          "country": "FR",
          "jockey": "Lorcan Williams",
          "trainer": "Jonjo & A.J. O'Neill",
          "form": "6-",
          "age": "5",
          "weight": "11-2",
          "draw": "",
          "odds_str": "22/1",
          "odds_dec": 23.0,
          "silk_url": "https://images.timeform.com/silks/opt/00051328.png",
          "score": 17.6,
          "components": {
            "odds_value": 0,
            "recent_form": 25.0,
            "consistency": 0,
            "jockey": 60.0,
            "weight": 0.0,
            "absence_pen": 0.0,
            "going_factor": 1.05
          },
          "recommendation": {
            "type": "Skip",
            "confidence": 7,
            "label": "Skip",
            "reasoning": "poor recent form"
          }
        }
      ]
    },
    {
      "id": "leicester-2025",
      "course": "Leicester",
      "time": "20:25",
      "title": "Picnic At The Races Monday 25Th May Book Now Handicap",
      "distance": "1m",
      "going": "Good to Firm",
      "race_class": "",
      "prize": "",
      "num_runners": 10,
      "ew_places": 3,
      "date": "2026-05-09",
      "runners": [
        {
          "horse": "TONAL",
          "country": "FR",
          "jockey": "Ryan Kavanagh",
          "trainer": "Ian Williams",
          "form": "1121-1315",
          "age": "6",
          "weight": "9-6",
          "draw": "",
          "odds_str": "4/1",
          "odds_dec": 999.0,
          "silk_url": "https://images.timeform.com/silks/opt/00860093.png",
          "score": 48.5,
          "components": {
            "odds_value": 0,
            "recent_form": 73.0,
            "consistency": 87.5,
            "jockey": 60.0,
            "weight": 20.0,
            "absence_pen": 0.0,
            "going_factor": 1.05
          },
          "recommendation": {
            "type": "Skip",
            "confidence": 19,
            "label": "Skip",
            "reasoning": "solid recent form; consistent placer (87% placed)"
          }
        },
        {
          "horse": "UP THE JAZZ",
          "country": "IRE",
          "jockey": "David Nolan",
          "trainer": "Richard & Peter Fahey",
          "form": "5068-8392",
          "age": "5",
          "weight": "9-9",
          "draw": "",
          "odds_str": "10/3",
          "odds_dec": 4.33,
          "silk_url": "https://images.timeform.com/silks/opt/00831345.png",
          "score": 47.1,
          "components": {
            "odds_value": 74.4,
            "recent_form": 44.3,
            "consistency": 25.0,
            "jockey": 60.0,
            "weight": 0.0,
            "absence_pen": 0.0,
            "going_factor": 1.05
          },
          "recommendation": {
            "type": "Skip",
            "confidence": 18,
            "label": "Skip",
            "reasoning": "moderate form; placed last time out"
          }
        },
        {
          "horse": "SUPER HIT",
          "country": "FR",
          "jockey": "Luke Morris",
          "trainer": "James Owen",
          "form": "0205-3272",
          "age": "5",
          "weight": "9-8",
          "draw": "",
          "odds_str": "7/1",
          "odds_dec": 8.0,
          "silk_url": "https://images.timeform.com/silks/opt/00886663.png",
          "score": 46.6,
          "components": {
            "odds_value": 35.2,
            "recent_form": 60.7,
            "consistency": 50.0,
            "jockey": 60.0,
            "weight": 6.7,
            "absence_pen": 0.0,
            "going_factor": 1.05
          },
          "recommendation": {
            "type": "Skip",
            "confidence": 18,
            "label": "Skip",
            "reasoning": "solid recent form; placed last time out; consistent placer (50% placed)"
          }
        },
        {
          "horse": "SHARMA D&#39;AMOUR",
          "country": "GB",
          "jockey": "Jack Nicholls",
          "trainer": "Denis Coakley",
          "form": "468478-52",
          "age": "4",
          "weight": "8-8",
          "draw": "",
          "odds_str": "13/2",
          "odds_dec": 7.5,
          "silk_url": "https://images.timeform.com/silks/opt/00884565.png",
          "score": 46.2,
          "components": {
            "odds_value": 38.3,
            "recent_form": 46.0,
            "consistency": 12.5,
            "jockey": 60.0,
            "weight": 100.0,
            "absence_pen": 0.0,
            "going_factor": 1.05
          },
          "recommendation": {
            "type": "Skip",
            "confidence": 18,
            "label": "Skip",
            "reasoning": "moderate form; placed last time out"
          }
        },
        {
          "horse": "YOKKELL",
          "country": "IRE",
          "jockey": "Kieran O'Neill",
          "trainer": "Adrian Wintle",
          "form": "905087-63",
          "age": "7",
          "weight": "9-6",
          "draw": "",
          "odds_str": "3/1",
          "odds_dec": 4.0,
          "silk_url": "https://images.timeform.com/silks/opt/00870286.png",
          "score": 46.2,
          "components": {
            "odds_value": 81.5,
            "recent_form": 35.3,
            "consistency": 12.5,
            "jockey": 60.0,
            "weight": 20.0,
            "absence_pen": 0.0,
            "going_factor": 1.05
          },
          "recommendation": {
            "type": "Skip",
            "confidence": 18,
            "label": "Skip",
            "reasoning": "moderate form"
          }
        },
        {
          "horse": "THE SWEET ESCAPE",
          "country": "GB",
          "jockey": "Rowan Scott",
          "trainer": "David Loughnane",
          "form": "4366-8616",
          "age": "4",
          "weight": "9-6",
          "draw": "",
          "odds_str": "5/1",
          "odds_dec": 6.0,
          "silk_url": "https://images.timeform.com/silks/opt/00834206.png",
          "score": 42.5,
          "components": {
            "odds_value": 50.6,
            "recent_form": 43.0,
            "consistency": 25.0,
            "jockey": 60.0,
            "weight": 20.0,
            "absence_pen": 0.0,
            "going_factor": 1.05
          },
          "recommendation": {
            "type": "Skip",
            "confidence": 16,
            "label": "Skip",
            "reasoning": "moderate form"
          }
        },
        {
          "horse": "STAR START",
          "country": "IRE",
          "jockey": "James Sullivan",
          "trainer": "Ruth Carr",
          "form": "12F26-953",
          "age": "6",
          "weight": "9-3",
          "draw": "",
          "odds_str": "9/1",
          "odds_dec": 10.0,
          "silk_url": "https://images.timeform.com/silks/opt/00071478.png",
          "score": 40.5,
          "components": {
            "odds_value": 25.9,
            "recent_form": 43.0,
            "consistency": 41.0,
            "jockey": 60.0,
            "weight": 40.0,
            "absence_pen": 0.0,
            "going_factor": 1.05
          },
          "recommendation": {
            "type": "Skip",
            "confidence": 16,
            "label": "Skip",
            "reasoning": "moderate form; consistent placer (50% placed)"
          }
        },
        {
          "horse": "MERCURIUS POWER",
          "country": "IRE",
          "jockey": "Darragh Keenan",
          "trainer": "Jessica Macey",
          "form": "327-53366",
          "age": "8",
          "weight": "9-1",
          "draw": "",
          "odds_str": "25/1",
          "odds_dec": 26.0,
          "silk_url": "https://images.timeform.com/silks/opt/00877545A.png",
          "score": 36.1,
          "components": {
            "odds_value": 3.1,
            "recent_form": 39.3,
            "consistency": 50.0,
            "jockey": 60.0,
            "weight": 53.3,
            "absence_pen": 0.0,
            "going_factor": 1.05
          },
          "recommendation": {
            "type": "Skip",
            "confidence": 14,
            "label": "Skip",
            "reasoning": "moderate form; consistent placer (50% placed)"
          }
        },
        {
          "horse": "STUDY UP",
          "country": "GB",
          "jockey": "Jonny Peate",
          "trainer": "Mark Loughnane",
          "form": "4839-8373",
          "age": "5",
          "weight": "9-5",
          "draw": "",
          "odds_str": "25/1",
          "odds_dec": 26.0,
          "silk_url": "https://images.timeform.com/silks/opt/00891217.png",
          "score": 32.7,
          "components": {
            "odds_value": 3.1,
            "recent_form": 43.3,
            "consistency": 37.5,
            "jockey": 60.0,
            "weight": 26.7,
            "absence_pen": 0.0,
            "going_factor": 1.05
          },
          "recommendation": {
            "type": "Skip",
            "confidence": 13,
            "label": "Skip",
            "reasoning": "moderate form"
          }
        },
        {
          "horse": "UNION ISLAND",
          "country": "IRE",
          "jockey": "Jack Callan",
          "trainer": "Charlie Johnston",
          "form": "48-631470",
          "age": "5",
          "weight": "9-7",
          "draw": "",
          "odds_str": "18/1",
          "odds_dec": 19.0,
          "silk_url": "https://images.timeform.com/silks/opt/00879385.png",
          "score": 29.0,
          "components": {
            "odds_value": 8.4,
            "recent_form": 37.7,
            "consistency": 25.0,
            "jockey": 60.0,
            "weight": 13.3,
            "absence_pen": 0.0,
            "going_factor": 1.05
          },
          "recommendation": {
            "type": "Skip",
            "confidence": 11,
            "label": "Skip",
            "reasoning": "moderate form"
          }
        }
      ]
    }
  ]
}